Workbook
Name Categories: Lists!$B$2:$B$21
Name Category: Lists!#REF!
Name Cities: Lists!$A$2:$A$21
Name City: Lists!#REF!
Name Costumer_s_Name: Lists!$H$2:$H$21
Name Dicount: Lists!$I$2:$I$21
Name Payment_Methods: Lists!$G$2:$G$21
Name Product: Lists!#REF!
Name Products: Lists!$D$2:$D$21
Name Region: Lists!$C$2:$C$21
Name Salespersons: Lists!$F$2:$F$21
Name Slicer_Category: #N/A
Name Slicer_Payment_Method: #N/A
Name Slicer_Product: #N/A
Name Slicer_Region: #N/A
Name Slicer_Sales_person: #N/A
Name Unit_Price: Lists!#REF!

Sheet Lists
A1: Cities | B1: Categories | C1: Region | D1: Products | E1: Unit Price | F1: Salespersons | G1: Payment Methods | H1: Customer Names | I1: Discount
A2: Karachi | B2: Electronics | C2: East | D2: Laptop | E2: 85000 | F2: Ali | G2: Cash | H2: Ali Khan | I2: 0.2 | J2: Laptop | K2: Electronics
A3: Lahore | B3: Furniture | C3: West | D3: Monitor | E3: 30000 | F3: Ahmed | G3: Debit Card | H3: Ahmed Raza | I3: 0.05 | J3: Monitor | K3: Electronics | L3: Total Prices
A4: Islamabad | B4: Office Supplies | C4: South | D4: Keyboard | E4: 4000 | F4: Ayesha | G4: Credit Card | H4: Ayesha Malik | I4: 0.25 | J4: Keyboard | K4: Electronics
A5: Rawalpindi | C5: South East | D5: Mouse | E5: 2500 | F5: Fatima | G5: Bank Transfer | H5: Fatima Noor | I5: 0.1 | J5: Mouse | K5: Electronics
A6: Faisalabad | C6: South West | D6: Printer | E6: 28000 | F6: Hamza | H6: Hamza Ali | I6: 0.25 | J6: Printer | K6: Electronics
A7: Peshawar | C7: North | D7: Office Chair | E7: 12000 | F7: Bilal | H7: Sara Ahmed | I7: 0.15 | J7: Office Chair | K7: Furniture
A8: Multan | D8: Office Desk | E8: 22000 | F8: Zain | H8: Usman Khan | I8: 0.05 | J8: Office Desk | K8: Furniture
A9: Hyderabad | D9: Notebook | E9: 350 | F9: Sara | H9: Hina Shah | I9: 0.05 | J9: Notebook | K9: Office Supplies
A10: Quetta | D10: Printer Paper | E10: 1200 | F10: Usman | H10: Bilal Ahmed | I10: 0.15 | J10: Printer Paper | K10: Office Supplies
A11: Sialkot | D11: Calculator | E11: 1500 | F11: Hina | H11: Zain Malik | I11: 0.25 | J11: Calculator | K11: Office Supplies
D12: USB Drive | E12: 2000 | H12: Maham Khan | I12: 0.05 | J12: USB Drive | K12: Electronics
D13: Headphones | E13: 5000 | H13: Saad Raza | I13: 0.05 | J13: Headphones | K13: Electronics
H14: Sana Ali
H15: Hassan Ahmed
H16: Iqra Khan
H17: Danish Malik
H18: Mariam Noor
H19: Talha Ahmed
H20: Laiba Khan
H21: Owais Raza

Sheet Raw Data
A1: Order ID | B1: Order Date | C1: Customer Name | D1: City | E1: Region | F1: Product | G1: Category | H1: Quantity | I1: Unit Price | J1: Discount% | K1: Total Sales | L1: Sales person | M1: Payment Method | N1: Price Status
A2: ="ORD"&TEXT(ROW()-1,"0000") -> ORD0001 | B2: 45407 | C2: Usman Khan | D2: Quetta | E2: South West | F2: Office Desk | G2: =_xlfn.XLOOKUP(F2,Lists!$J$2:$J$13,Lists!$K$2:$K$13,"Not Found") -> Furniture | H2: 5 | I2: =_xlfn.XLOOKUP(F2,Lists!$D$2:$D$13,Lists!$E$2:$E$13,"Not Found") -> 22000 | J2: 0.25 | K2: =H2*I2*(1-J2) -> 82500 | L2: Ali | M2: Bank Transfer | N2: =IF(I2=_xlfn.XLOOKUP(F2,Lists!$D$2:$D$13,Lists!$E$2:$E$13,"Not Found"),"OK","Check Price") -> OK
A3: ="ORD"&TEXT(ROW()-1,"0000") -> ORD0002 | B3: 45729 | C3: Zain Malik | D3: Rawalpindi | E3: South | F3: Keyboard | G3: Electronics | H3: 6 | I3: 12000 | J3: 0.25 | K3: =H3*I3*(1-J3) -> 54000 | L3: Ayesha | M3: Debit Card | N3: =IF(I3=_xlfn.XLOOKUP(F3,Lists!$D$2:$D$13,Lists!$E$2:$E$13,"Not Found"),"OK","Check Price") -> Check Price
A4: ="ORD"&TEXT(ROW()-1,"0000") -> ORD0003 | B4: 45848 | C4: Saad Raza | D4: Sialkot | E4: North | F4: Mouse | G4: Furniture | H4: 6 | I4: 350 | J4: 0.05 | K4: =H4*I4*(1-J4) -> 1995 | L4: Zain | M4: Cash | N4: =IF(I4=_xlfn.XLOOKUP(F4,Lists!$D$2:$D$13,Lists!$E$2:$E$13,"Not Found"),"OK","Check Price") -> Check Price
A5: ="ORD"&TEXT(ROW()-1,"0000") -> ORD0004 | B5: 45400 | C5: Saad Raza | D5: Faisalabad | E5: South West | F5: Calculator | G5: =_xlfn.XLOOKUP(F5,Lists!$J$2:$J$13,Lists!$K$2:$K$13,"Not Found") -> Office Supplies | H5: 4 | I5: =_xlfn.XLOOKUP(F5,Lists!$D$2:$D$13,Lists!$E$2:$E$13,"Not Found") -> 1500 | J5: 0.15 | K5: =H5*I5*(1-J5) -> 5100 | L5: Ali | M5: Debit Card | N5: =IF(I5=_xlfn.XLOOKUP(F5,Lists!$D$2:$D$13,Lists!$E$2:$E$13,"Not Found"),"OK","Check Price") -> OK
A6: ="ORD"&TEXT(ROW()-1,"0000") -> ORD0005 | B6: 45506 | C6: Mariam Noor | D6: Hyderabad | E6: West | F6: Calculator | G6: =_xlfn.XLOOKUP(F6,Lists!$J$2:$J$13,Lists!$K$2:$K$13,"Not Found") -> Office Supplies | H6: 2 | I6: =_xlfn.XLOOKUP(F6,Lists!$D$2:$D$13,Lists!$E$2:$E$13,"Not Found") -> 1500 | J6: 0.1 | K6: =H6*I6*(1-J6) -> 2700 | L6: Ayesha | M6: Bank Transfer | N6: =IF(I6=_xlfn.XLOOKUP(F6,Lists!$D$2:$D$13,Lists!$E$2:$E$13,"Not Found"),"OK","Check Price") -> OK
A7: ="ORD"&TEXT(ROW()-1,"0000") -> ORD0006 | B7: 45477 | C7: Sara Ahmed | D7: Karachi | E7: West | F7: Monitor | G7: Office Supplies | H7: 6 | I7: 12000 | J7: 0.25 | K7: =H7*I7*(1-J7) -> 54000 | L7: Zain | M7: Bank Transfer | N7: =IF(I7=_xlfn.XLOOKUP(F7,Lists!$D$2:$D$13,Lists!$E$2:$E$13,"Not Found"),"OK","Check Price") -> Check Price
A8: ="ORD"&TEXT(ROW()-1,"0000") -> ORD0007 | B8: 45740 | C8: Owais Raza | D8: Peshawar | E8: South | F8: USB Drive | G8: Office Supplies | H8: 10 | I8: 22000 | J8: 0.2 | K8: =H8*I8*(1-J8) -> 176000 | L8: Bilal | M8: Bank Transfer | N8: =IF(I8=_xlfn.XLOOKUP(F8,Lists!$D$2:$D$13,Lists!$E$2:$E$13,"Not Found"),"OK","Check Price") -> Check Price
A9: ="ORD"&TEXT(ROW()-1,"0000") -> ORD0008 | B9: 45720 | C9: Danish Malik | D9: Rawalpindi | E9: South | F9: Laptop | G9: =_xlfn.XLOOKUP(F9,Lists!$J$2:$J$13,Lists!$K$2:$K$13,"Not Found") -> Electronics | H9: 5 | I9: =_xlfn.XLOOKUP(F9,Lists!$D$2:$D$13,Lists!$E$2:$E$13,"Not Found") -> 85000 | J9: 0.2 | K9: =H9*I9*(1-J9) -> 340000 | L9: Ali | M9: Cash | N9: =IF(I9=_xlfn.XLOOKUP(F9,Lists!$D$2:$D$13,Lists!$E$2:$E$13,"Not Found"),"OK","Check Price") -> OK
A10: ="ORD"&TEXT(ROW()-1,"0000") -> ORD0009 | B10: 45528 | C10: Iqra Khan | D10: Faisalabad | E10: South | F10: Calculator | G10: =_xlfn.XLOOKUP(F10,Lists!$J$2:$J$13,Lists!$K$2:$K$13,"Not Found") -> Office Supplies | H10: 7 | I10: =_xlfn.XLOOKUP(F10,Lists!$D$2:$D$13,Lists!$E$2:$E$13,"Not Found") -> 1500 | J10: 0.15 | K10: =H10*I10*(1-J10) -> 8925 | L10: Sara | M10: Debit Card | N10: =IF(I10=_xlfn.XLOOKUP(F10,Lists!$D$2:$D$13,Lists!$E$2:$E$13,"Not Found"),"OK","Check Price") -> OK
A11: ="ORD"&TEXT(ROW()-1,"0000") -> ORD0010 | B11: 45912 | C11: Saad Raza | D11: Lahore | E11: North | F11: Monitor | G11: Office Supplies | H11: 7 | I11: 85000 | J11: 0.25 | K11: =H11*I11*(1-J11) -> 446250 | L11: Ayesha | M11: Cash | N11: =IF(I11=_xlfn.XLOOKUP(F11,Lists!$D$2:$D$13,Lists!$E$2:$E$13,"Not Found"),"OK","Check Price") -> Check Price
A12: ="ORD"&TEXT(ROW()-1,"0000") -> ORD0011 | B12: 45533 | C12: Sana Ali | D12: Multan | E12: South East | F12: Office Desk | G12: =_xlfn.XLOOKUP(F12,Lists!$J$2:$J$13,Lists!$K$2:$K$13,"Not Found") -> Furniture | H12: 2 | I12: =_xlfn.XLOOKUP(F12,Lists!$D$2:$D$13,Lists!$E$2:$E$13,"Not Found") -> 22000 | J12: 0.2 | K12: =H12*I12*(1-J12) -> 35200 | L12: Ahmed | M12: Bank Transfer | N12: =IF(I12=_xlfn.XLOOKUP(F12,Lists!$D$2:$D$13,Lists!$E$2:$E$13,"Not Found"),"OK","Check Price") -> OK
A13: ="ORD"&TEXT(ROW()-1,"0000") -> ORD0012 | B13: 46005 | C13: Saad Raza | D13: Rawalpindi | E13: South East | F13: Notebook | G13: Office Supplies | H13: 1 | I13: 350 | J13: 0.1 | K13: =H13*I13*(1-J13) -> 315 | L13: Fatima | M13: Cash | N13: =IF(I13=_xlfn.XLOOKUP(F13,Lists!$D$2:$D$13,Lists!$E$2:$E$13,"Not Found"),"OK","Check Price") -> OK
A14: ="ORD"&TEXT(ROW()-1,"0000") -> ORD0013 | B14: 45356 | C14: Sara Ahmed | D14: Quetta | E14: West | F14: USB Drive | G14: Electronics | H14: 1 | I14: 1500 | J14: 0.2 | K14: =H14*I14*(1-J14) -> 1200 | L14: Ali | M14: Cash | N14: =IF(I14=_xlfn.XLOOKUP(F14,Lists!$D$2:$D$13,Lists!$E$2:$E$13,"Not Found"),"OK","Check Price") -> Check Price
A15: ="ORD"&TEXT(ROW()-1,"0000") -> ORD0014 | B15: 45365 | C15: Hamza Ali | D15: Hyderabad | E15: South East | F15: Headphones | G15: Office Supplies | H15: 5 | I15: 85000 | J15: 0.2 | K15: =H15*I15*(1-J15) -> 340000 | L15: Bilal | M15: Debit Card | N15: =IF(I15=_xlfn.XLOOKUP(F15,Lists!$D$2:$D$13,Lists!$E$2:$E$13,"Not Found"),"OK","Check Price") -> Check Price
A16: ="ORD"&TEXT(ROW()-1,"0000") -> ORD0015 | B16: 45779 | C16: Ali Khan | D16: Faisalabad | E16: South East | F16: Keyboard | G16: Electronics | H16: 6 | I16: 5000 | J16: 0.1 | K16: =H16*I16*(1-J16) -> 27000 | L16: Hamza | M16: Credit Card | N16: =IF(I16=_xlfn.XLOOKUP(F16,Lists!$D$2:$D$13,Lists!$E$2:$E$13,"Not Found"),"OK","Check Price") -> Check Price
A17: ="ORD"&TEXT(ROW()-1,"0000") -> ORD0016 | B17: 45912 | C17: Zain Malik | D17: Islamabad | E17: South West | F17: Office Desk | G17: =_xlfn.XLOOKUP(F17,Lists!$J$2:$J$13,Lists!$K$2:$K$13,"Not Found") -> Furniture | H17: 6 | I17: =_xlfn.XLOOKUP(F17,Lists!$D$2:$D$13,Lists!$E$2:$E$13,"Not Found") -> 22000 | J17: 0.15 | K17: =H17*I17*(1-J17) -> 112200 | L17: Ayesha | M17: Debit Card | N17: =IF(I17=_xlfn.XLOOKUP(F17,Lists!$D$2:$D$13,Lists!$E$2:$E$13,"Not Found"),"OK","Check Price") -> OK
A18: ="ORD"&TEXT(ROW()-1,"0000") -> ORD0017 | B18: 45374 | C18: Fatima Noor | D18: Quetta | E18: South | F18: Keyboard | G18: Office Supplies | H18: 9 | I18: 28000 | J18: 0.05 | K18: =H18*I18*(1-J18) -> 239400 | L18: Usman | M18: Cash | N18: =IF(I18=_xlfn.XLOOKUP(F18,Lists!$D$2:$D$13,Lists!$E$2:$E$13,"Not Found"),"OK","Check Price") -> Check Price
A19: ="ORD"&TEXT(ROW()-1,"0000") -> ORD0018 | B19: 45929 | C19: Hassan Ahmed | D19: Islamabad | E19: West | F19: Printer | G19: Electronics | H19: 8 | I19: 28000 | J19: 0.25 | K19: =H19*I19*(1-J19) -> 168000 | L19: Ayesha | M19: Credit Card | N19: =IF(I19=_xlfn.XLOOKUP(F19,Lists!$D$2:$D$13,Lists!$E$2:$E$13,"Not Found"),"OK","Check Price") -> OK
A20: ="ORD"&TEXT(ROW()-1,"0000") -> ORD0019 | B20: 45627 | C20: Iqra Khan | D20: Rawalpindi | E20: South West | F20: Printer Paper | G20: Office Supplies | H20: 2 | I20: 4000 | J20: 0.2 | K20: =H20*I20*(1-J20) -> 6400 | L20: Fatima | M20: Bank Transfer | N20: =IF(I20=_xlfn.XLOOKUP(F20,Lists!$D$2:$D$13,Lists!$E$2:$E$13,"Not Found"),"OK","Check Price") -> Check Price
A21: ="ORD"&TEXT(ROW()-1,"0000") -> ORD0020 | B21: 45401 | C21: Talha Ahmed | D21: Lahore | E21: South West | F21: Laptop | G21: =_xlfn.XLOOKUP(F21,Lists!$J$2:$J$13,Lists!$K$2:$K$13,"Not Found") -> Electronics | H21: 4 | I21: =_xlfn.XLOOKUP(F21,Lists!$D$2:$D$13,Lists!$E$2:$E$13,"Not Found") -> 85000 | J21: 0.2 | K21: =H21*I21*(1-J21) -> 272000 | L21: Fatima | M21: Debit Card | N21: =IF(I21=_xlfn.XLOOKUP(F21,Lists!$D$2:$D$13,Lists!$E$2:$E$13,"Not Found"),"OK","Check Price") -> OK
A22: ="ORD"&TEXT(ROW()-1,"0000") -> ORD0021 | B22: 45463 | C22: Danish Malik | D22: Islamabad | E22: North | F22: USB Drive | G22: Office Supplies | H22: 10 | I22: 12000 | J22: 0.05 | K22: =H22*I22*(1-J22) -> 114000 | L22: Zain | M22: Bank Transfer | N22: =IF(I22=_xlfn.XLOOKUP(F22,Lists!$D$2:$D$13,Lists!$E$2:$E$13,"Not Found"),"OK","Check Price") -> Check Price
A23: ="ORD"&TEXT(ROW()-1,"0000") -> ORD0022 | B23: 45633 | C23: Ahmed Raza | D23: Lahore | E23: West | F23: Office Desk | G23: =_xlfn.XLOOKUP(F23,Lists!$J$2:$J$13,Lists!$K$2:$K$13,"Not Found") -> Furniture | H23: 5 | I23: =_xlfn.XLOOKUP(F23,Lists!$D$2:$D$13,Lists!$E$2:$E$13,"Not Found") -> 22000 | J23: 0.2 | K23: =H23*I23*(1-J23) -> 88000 | L23: Sara | M23: Cash | N23: =IF(I23=_xlfn.XLOOKUP(F23,Lists!$D$2:$D$13,Lists!$E$2:$E$13,"Not Found"),"OK","Check Price") -> OK
A24: ="ORD"&TEXT(ROW()-1,"0000") -> ORD0023 | B24: 45770 | C24: Sana Ali | D24: Peshawar | E24: North | F24: Printer Paper | G24: Office Supplies | H24: 4 | I24: 30000 | J24: 0.1 | K24: =H24*I24*(1-J24) -> 108000 | L24: Bilal | M24: Cash | N24: =IF(I24=_xlfn.XLOOKUP(F24,Lists!$D$2:$D$13,Lists!$E$2:$E$13,"Not Found"),"OK","Check Price") -> Check Price
A25: ="ORD"&TEXT(ROW()-1,"0000") -> ORD0024 | B25: 45787 | C25: Mariam Noor | D25: Karachi | E25: South East | F25: Headphones | G25: Furniture | H25: 7 | I25: 1500 | J25: 0.2 | K25: =H25*I25*(1-J25) -> 8400 | L25: Ali | M25: Cash | N25: =IF(I25=_xlfn.XLOOKUP(F25,Lists!$D$2:$D$13,Lists!$E$2:$E$13,"Not Found"),"OK","Check Price") -> Check Price
A26: ="ORD"&TEXT(ROW()-1,"0000") -> ORD0025 | B26: 45965 | C26: Danish Malik | D26: Sialkot | E26: South West | F26: Office Desk | G26: =_xlfn.XLOOKUP(F26,Lists!$J$2:$J$13,Lists!$K$2:$K$13,"Not Found") -> Furniture | H26: 6 | I26: =_xlfn.XLOOKUP(F26,Lists!$D$2:$D$13,Lists!$E$2:$E$13,"Not Found") -> 22000 | J26: 0.25 | K26: =H26*I26*(1-J26) -> 99000 | L26: Ayesha | M26: Debit Card | N26: =IF(I26=_xlfn.XLOOKUP(F26,Lists!$D$2:$D$13,Lists!$E$2:$E$13,"Not Found"),"OK","Check Price") -> OK
A27: ="ORD"&TEXT(ROW()-1,"0000") -> ORD0026 | B27: 45517 | C27: Mariam Noor | D27: Lahore | E27: South West | F27: Printer | G27: Office Supplies | H27: 2 | I27: 30000 | J27: 0.25 | K27: =H27*I27*(1-J27) -> 45000 | L27: Ali | M27: Cash | N27: =IF(I27=_xlfn.XLOOKUP(F27,Lists!$D$2:$D$13,Lists!$E$2:$E$13,"Not Found"),"OK","Check Price") -> Check Price
A28: ="ORD"&TEXT(ROW()-1,"0000") -> ORD0027 | B28: 45382 | C28: Saad Raza | D28: Quetta | E28: South West | F28: Printer Paper | G28: Office Supplies | H28: 6 | I28: 4000 | J28: 0.15 | K28: =H28*I28*(1-J28) -> 20400 | L28: Hamza | M28: Bank Transfer | N28: =IF(I28=_xlfn.XLOOKUP(F28,Lists!$D$2:$D$13,Lists!$E$2:$E$13,"Not Found"),"OK","Check Price") -> Check Price
A29: ="ORD"&TEXT(ROW()-1,"0000") -> ORD0028 | B29: 45512 | C29: Mariam Noor | D29: Hyderabad | E29: West | F29: Office Desk | G29: =_xlfn.XLOOKUP(F29,Lists!$J$2:$J$13,Lists!$K$2:$K$13,"Not Found") -> Furniture | H29: 5 | I29: =_xlfn.XLOOKUP(F29,Lists!$D$2:$D$13,Lists!$E$2:$E$13,"Not Found") -> 22000 | J29: 0.1 | K29: =H29*I29*(1-J29) -> 99000 | L29: Fatima | M29: Cash | N29: =IF(I29=_xlfn.XLOOKUP(F29,Lists!$D$2:$D$13,Lists!$E$2:$E$13,"Not Found"),"OK","Check Price") -> OK
A30: ="ORD"&TEXT(ROW()-1,"0000") -> ORD0029 | B30: 45392 | C30: Danish Malik | D30: Hyderabad | E30: South West | F30: Monitor | G30: Office Supplies | H30: 1 | I30: 5000 | J30: 0.25 | K30: =H30*I30*(1-J30) -> 3750 | L30: Usman | M30: Cash | N30: =IF(I30=_xlfn.XLOOKUP(F30,Lists!$D$2:$D$13,Lists!$E$2:$E$13,"Not Found"),"OK","Check Price") -> Check Price
A31: ="ORD"&TEXT(ROW()-1,"0000") -> ORD0030 | B31: 45830 | C31: Saad Raza | D31: Sialkot | E31: South West | F31: Laptop | G31: =_xlfn.XLOOKUP(F31,Lists!$J$2:$J$13,Lists!$K$2:$K$13,"Not Found") -> Electronics | H31: 6 | I31: =_xlfn.XLOOKUP(F31,Lists!$D$2:$D$13,Lists!$E$2:$E$13,"Not Found") -> 85000 | J31: 0.1 | K31: =H31*I31*(1-J31) -> 459000 | L31: Usman | M31: Bank Transfer | N31: =IF(I31=_xlfn.XLOOKUP(F31,Lists!$D$2:$D$13,Lists!$E$2:$E$13,"Not Found"),"OK","Check Price") -> OK
A32: ="ORD"&TEXT(ROW()-1,"0000") -> ORD0031 | B32: 45331 | C32: Ayesha Malik | D32: Quetta | E32: South East | F32: Mouse | G32: Electronics | H32: 5 | I32: 12000 | J32: 0.25 | K32: =H32*I32*(1-J32) -> 45000 | L32: Fatima | M32: Credit Card | N32: =IF(I32=_xlfn.XLOOKUP(F32,Lists!$D$2:$D$13,Lists!$E$2:$E$13,"Not Found"),"OK","Check Price") -> Check Price
A33: ="ORD"&TEXT(ROW()-1,"0000") -> ORD0032 | B33: 45750 | C33: Ahmed Raza | D33: Quetta | E33: South West | F33: Mouse | G33: Office Supplies | H33: 1 | I33: 2500 | J33: 0.05 | K33: =H33*I33*(1-J33) -> 2375 | L33: Sara | M33: Cash | N33: =IF(I33=_xlfn.XLOOKUP(F33,Lists!$D$2:$D$13,Lists!$E$2:$E$13,"Not Found"),"OK","Check Price") -> OK
A34: ="ORD"&TEXT(ROW()-1,"0000") -> ORD0033 | B34: 45848 | C34: Mariam Noor | D34: Quetta | E34: West | F34: Printer | G34: Furniture | H34: 10 | I34: 22000 | J34: 0.2 | K34: =H34*I34*(1-J34) -> 176000 | L34: Bilal | M34: Cash | N34: =IF(I34=_xlfn.XLOOKUP(F34,Lists!$D$2:$D$13,Lists!$E$2:$E$13,"Not Found"),"OK","Check Price") -> Check Price
A35: ="ORD"&TEXT(ROW()-1,"0000") -> ORD0034 | B35: 45417 | C35: Danish Malik | D35: Faisalabad | E35: South West | F35: Notebook | G35: Furniture | H35: 4 | I35: 2500 | J35: 0.1 | K35: =H35*I35*(1-J35) -> 9000 | L35: Hina | M35: Cash | N35: =IF(I35=_xlfn.XLOOKUP(F35,Lists!$D$2:$D$13,Lists!$E$2:$E$13,"Not Found"),"OK","Check Price") -> Check Price
A36: ="ORD"&TEXT(ROW()-1,"0000") -> ORD0035 | B36: 45538 | C36: Bilal Ahmed | D36: Sialkot | E36: North | F36: Mouse | G36: Electronics | H36: 3 | I36: 2500 | J36: 0.1 | K36: =H36*I36*(1-J36) -> 6750 | L36: Sara | M36: Cash | N36: =IF(I36=_xlfn.XLOOKUP(F36,Lists!$D$2:$D$13,Lists!$E$2:$E$13,"Not Found"),"OK","Check Price") -> OK
A37: ="ORD"&TEXT(ROW()-1,"0000") -> ORD0036 | B37: 45863 | C37: Sana Ali | D37: Quetta | E37: East | F37: Printer | G37: Furniture | H37: 7 | I37: 12000 | J37: 0.05 | K37: =H37*I37*(1-J37) -> 79800 | L37: Fatima | M37: Credit Card | N37: =IF(I37=_xlfn.XLOOKUP(F37,Lists!$D$2:$D$13,Lists!$E$2:$E$13,"Not Found"),"OK","Check Price") -> Check Price
A38: ="ORD"&TEXT(ROW()-1,"0000") -> ORD0037 | B38: 45898 | C38: Ali Khan | D38: Faisalabad | E38: South West | F38: Laptop | G38: =_xlfn.XLOOKUP(F38,Lists!$J$2:$J$13,Lists!$K$2:$K$13,"Not Found") -> Electronics | H38: 8 | I38: =_xlfn.XLOOKUP(F38,Lists!$D$2:$D$13,Lists!$E$2:$E$13,"Not Found") -> 85000 | J38: 0.05 | K38: =H38*I38*(1-J38) -> 646000 | L38: Ahmed | M38: Credit Card | N38: =IF(I38=_xlfn.XLOOKUP(F38,Lists!$D$2:$D$13,Lists!$E$2:$E$13,"Not Found"),"OK","Check Price") -> OK
A39: ="ORD"&TEXT(ROW()-1,"0000") -> ORD0038 | B39: 45307 | C39: Hina Shah | D39: Rawalpindi | E39: East | F39: Notebook | G39: Electronics | H39: 5 | I39: 2500 | J39: 0.25 | K39: =H39*I39*(1-J39) -> 9375 | L39: Ali | M39: Bank Transfer | N39: =IF(I39=_xlfn.XLOOKUP(F39,Lists!$D$2:$D$13,Lists!$E$2:$E$13,"Not Found"),"OK","Check Price") -> Check Price
A40: ="ORD"&TEXT(ROW()-1,"0000") -> ORD0039 | B40: 45745 | C40: Danish Malik | D40: Peshawar | E40: South | F40: USB Drive | G40: Electronics | H40: 7 | I40: 30000 | J40: 0.25 | K40: =H40*I40*(1-J40) -> 157500 | L40: Usman | M40: Credit Card | N40: =IF(I40=_xlfn.XLOOKUP(F40,Lists!$D$2:$D$13,Lists!$E$2:$E$13,"Not Found"),"OK","Check Price") -> Check Price
A41: ="ORD"&TEXT(ROW()-1,"0000") -> ORD0040 | B41: 45504 | C41: Saad Raza | D41: Faisalabad | E41: South | F41: USB Drive | G41: Office Supplies | H41: 8 | I41: 30000 | J41: 0.2 | K41: =H41*I41*(1-J41) -> 192000 | L41: Ali | M41: Bank Transfer | N41: =IF(I41=_xlfn.XLOOKUP(F41,Lists!$D$2:$D$13,Lists!$E$2:$E$13,"Not Found"),"OK","Check Price") -> Check Price
A42: ="ORD"&TEXT(ROW()-1,"0000") -> ORD0041 | B42: 45993 | C42: Sara Ahmed | D42: Quetta | E42: West | F42: Office Chair | G42: Furniture | H42: 6 | I42: 2500 | J42: 0.1 | K42: =H42*I42*(1-J42) -> 13500 | L42: Usman | M42: Debit Card | N42: =IF(I42=_xlfn.XLOOKUP(F42,Lists!$D$2:$D$13,Lists!$E$2:$E$13,"Not Found"),"OK","Check Price") -> Check Price
A43: ="ORD"&TEXT(ROW()-1,"0000") -> ORD0042 | B43: 45621 | C43: Iqra Khan | D43: Rawalpindi | E43: North | F43: Monitor | G43: Electronics | H43: 9 | I43: 28000 | J43: 0.1 | K43: =H43*I43*(1-J43) -> 226800 | L43: Hamza | M43: Debit Card | N43: =IF(I43=_xlfn.XLOOKUP(F43,Lists!$D$2:$D$13,Lists!$E$2:$E$13,"Not Found"),"OK","Check Price") -> Check Price
A44: ="ORD"&TEXT(ROW()-1,"0000") -> ORD0043 | B44: 45298 | C44: Mariam Noor | D44: Lahore | E44: South East | F44: Printer Paper | G44: Office Supplies | H44: 4 | I44: 1200 | J44: 0.1 | K44: =H44*I44*(1-J44) -> 4320 | L44: Hamza | M44: Cash | N44: =IF(I44=_xlfn.XLOOKUP(F44,Lists!$D$2:$D$13,Lists!$E$2:$E$13,"Not Found"),"OK","Check Price") -> OK
A45: ="ORD"&TEXT(ROW()-1,"0000") -> ORD0044 | B45: 45335 | C45: Iqra Khan | D45: Rawalpindi | E45: South East | F45: Printer | G45: Office Supplies | H45: 1 | I45: 1500 | J45: 0.25 | K45: =H45*I45*(1-J45) -> 1125 | L45: Usman | M45: Cash | N45: =IF(I45=_xlfn.XLOOKUP(F45,Lists!$D$2:$D$13,Lists!$E$2:$E$13,"Not Found"),"OK","Check Price") -> Check Price
A46: ="ORD"&TEXT(ROW()-1,"0000") -> ORD0045 | B46: 45485 | C46: Talha Ahmed | D46: Lahore | E46: South East | F46: Laptop | G46: =_xlfn.XLOOKUP(F46,Lists!$J$2:$J$13,Lists!$K$2:$K$13,"Not Found") -> Electronics | H46: 3 | I46: =_xlfn.XLOOKUP(F46,Lists!$D$2:$D$13,Lists!$E$2:$E$13,"Not Found") -> 85000 | J46: 0.05 | K46: =H46*I46*(1-J46) -> 242250 | L46: Zain | M46: Debit Card | N46: =IF(I46=_xlfn.XLOOKUP(F46,Lists!$D$2:$D$13,Lists!$E$2:$E$13,"Not Found"),"OK","Check Price") -> OK
A47: ="ORD"&TEXT(ROW()-1,"0000") -> ORD0046 | B47: 45621 | C47: Hamza Ali | D47: Sialkot | E47: South West | F47: Monitor | G47: Office Supplies | H47: 9 | I47: 1500 | J47: 0.2 | K47: =H47*I47*(1-J47) -> 10800 | L47: Zain | M47: Debit Card | N47: =IF(I47=_xlfn.XLOOKUP(F47,Lists!$D$2:$D$13,Lists!$E$2:$E$13,"Not Found"),"OK","Check Price") -> Check Price
A48: ="ORD"&TEXT(ROW()-1,"0000") -> ORD0047 | B48: 46007 | C48: Bilal Ahmed | D48: Rawalpindi | E48: East | F48: USB Drive | G48: Electronics | H48: 1 | I48: 85000 | J48: 0.1 | K48: =H48*I48*(1-J48) -> 76500 | L48: Ali | M48: Cash | N48: =IF(I48=_xlfn.XLOOKUP(F48,Lists!$D$2:$D$13,Lists!$E$2:$E$13,"Not Found"),"OK","Check Price") -> Check Price
A49: ="ORD"&TEXT(ROW()-1,"0000") -> ORD0048 | B49: 45970 | C49: Ayesha Malik | D49: Rawalpindi | E49: South | F49: Office Desk | G49: =_xlfn.XLOOKUP(F49,Lists!$J$2:$J$13,Lists!$K$2:$K$13,"Not Found") -> Furniture | H49: 1 | I49: =_xlfn.XLOOKUP(F49,Lists!$D$2:$D$13,Lists!$E$2:$E$13,"Not Found") -> 22000 | J49: 0.05 | K49: =H49*I49*(1-J49) -> 20900 | L49: Hina | M49: Cash | N49: =IF(I49=_xlfn.XLOOKUP(F49,Lists!$D$2:$D$13,Lists!$E$2:$E$13,"Not Found"),"OK","Check Price") -> OK
A50: ="ORD"&TEXT(ROW()-1,"0000") -> ORD0049 | B50: 45544 | C50: Zain Malik | D50: Peshawar | E50: North | F50: USB Drive | G50: Furniture | H50: 2 | I50: 4000 | J50: 0.25 | K50: =H50*I50*(1-J50) -> 6000 | L50: Usman | M50: Credit Card | N50: =IF(I50=_xlfn.XLOOKUP(F50,Lists!$D$2:$D$13,Lists!$E$2:$E$13,"Not Found"),"OK","Check Price") -> Check Price
A51: ="ORD"&TEXT(ROW()-1,"0000") -> ORD0050 | B51: 45961 | C51: Zain Malik | D51: Islamabad | E51: West | F51: Mouse | G51: Electronics | H51: 4 | I51: 28000 | J51: 0.25 | K51: =H51*I51*(1-J51) -> 84000 | L51: Bilal | M51: Cash | N51: =IF(I51=_xlfn.XLOOKUP(F51,Lists!$D$2:$D$13,Lists!$E$2:$E$13,"Not Found"),"OK","Check Price") -> Check Price
A52: ="ORD"&TEXT(ROW()-1,"0000") -> ORD0051 | B52: 45568 | C52: Fatima Noor | D52: Multan | E52: South West | F52: Calculator | G52: =_xlfn.XLOOKUP(F52,Lists!$J$2:$J$13,Lists!$K$2:$K$13,"Not Found") -> Office Supplies | H52: 1 | I52: =_xlfn.XLOOKUP(F52,Lists!$D$2:$D$13,Lists!$E$2:$E$13,"Not Found") -> 1500 | J52: 0.2 | K52: =H52*I52*(1-J52) -> 1200 | L52: Zain | M52: Cash | N52: =IF(I52=_xlfn.XLOOKUP(F52,Lists!$D$2:$D$13,Lists!$E$2:$E$13,"Not Found"),"OK","Check Price") -> OK
A53: ="ORD"&TEXT(ROW()-1,"0000") -> ORD0052 | B53: 45828 | C53: Fatima Noor | D53: Faisalabad | E53: West | F53: Office Chair | G53: Office Supplies | H53: 5 | I53: 2500 | J53: 0.15 | K53: =H53*I53*(1-J53) -> 10625 | L53: Bilal | M53: Bank Transfer | N53: =IF(I53=_xlfn.XLOOKUP(F53,Lists!$D$2:$D$13,Lists!$E$2:$E$13,"Not Found"),"OK","Check Price") -> Check Price
A54: ="ORD"&TEXT(ROW()-1,"0000") -> ORD0053 | B54: 45300 | C54: Owais Raza | D54: Quetta | E54: North | F54: Printer | G54: Furniture | H54: 5 | I54: 5000 | J54: 0.05 | K54: =H54*I54*(1-J54) -> 23750 | L54: Usman | M54: Debit Card | N54: =IF(I54=_xlfn.XLOOKUP(F54,Lists!$D$2:$D$13,Lists!$E$2:$E$13,"Not Found"),"OK","Check Price") -> Check Price
A55: ="ORD"&TEXT(ROW()-1,"0000") -> ORD0054 | B55: 45702 | C55: Sana Ali | D55: Rawalpindi | E55: West | F55: Monitor | G55: Electronics | H55: 4 | I55: 85000 | J55: 0.25 | K55: =H55*I55*(1-J55) -> 255000 | L55: Ayesha | M55: Bank Transfer | N55: =IF(I55=_xlfn.XLOOKUP(F55,Lists!$D$2:$D$13,Lists!$E$2:$E$13,"Not Found"),"OK","Check Price") -> Check Price
A56: ="ORD"&TEXT(ROW()-1,"0000") -> ORD0055 | B56: 45323 | C56: Ali Khan | D56: Islamabad | E56: East | F56: Calculator | G56: =_xlfn.XLOOKUP(F56,Lists!$J$2:$J$13,Lists!$K$2:$K$13,"Not Found") -> Office Supplies | H56: 3 | I56: =_xlfn.XLOOKUP(F56,Lists!$D$2:$D$13,Lists!$E$2:$E$13,"Not Found") -> 1500 | J56: 0.2 | K56: =H56*I56*(1-J56) -> 3600 | L56: Hina | M56: Credit Card | N56: =IF(I56=_xlfn.XLOOKUP(F56,Lists!$D$2:$D$13,Lists!$E$2:$E$13,"Not Found"),"OK","Check Price") -> OK
A57: ="ORD"&TEXT(ROW()-1,"0000") -> ORD0056 | B57: 45927 | C57: Sara Ahmed | D57: Sialkot | E57: South East | F57: Calculator | G57: =_xlfn.XLOOKUP(F57,Lists!$J$2:$J$13,Lists!$K$2:$K$13,"Not Found") -> Office Supplies | H57: 2 | I57: =_xlfn.XLOOKUP(F57,Lists!$D$2:$D$13,Lists!$E$2:$E$13,"Not Found") -> 1500 | J57: 0.05 | K57: =H57*I57*(1-J57) -> 2850 | L57: Hamza | M57: Credit Card | N57: =IF(I57=_xlfn.XLOOKUP(F57,Lists!$D$2:$D$13,Lists!$E$2:$E$13,"Not Found"),"OK","Check Price") -> OK
A58: ="ORD"&TEXT(ROW()-1,"0000") -> ORD0057 | B58: 45787 | C58: Fatima Noor | D58: Lahore | E58: South East | F58: Office Desk | G58: =_xlfn.XLOOKUP(F58,Lists!$J$2:$J$13,Lists!$K$2:$K$13,"Not Found") -> Furniture | H58: 10 | I58: =_xlfn.XLOOKUP(F58,Lists!$D$2:$D$13,Lists!$E$2:$E$13,"Not Found") -> 22000 | J58: 0.1 | K58: =H58*I58*(1-J58) -> 198000 | L58: Usman | M58: Credit Card | N58: =IF(I58=_xlfn.XLOOKUP(F58,Lists!$D$2:$D$13,Lists!$E$2:$E$13,"Not Found"),"OK","Check Price") -> OK
A59: ="ORD"&TEXT(ROW()-1,"0000") -> ORD0058 | B59: 45298 | C59: Mariam Noor | D59: Peshawar | E59: South East | F59: Printer Paper | G59: Office Supplies | H59: 10 | I59: 30000 | J59: 0.25 | K59: =H59*I59*(1-J59) -> 225000 | L59: Hina | M59: Cash | N59: =IF(I59=_xlfn.XLOOKUP(F59,Lists!$D$2:$D$13,Lists!$E$2:$E$13,"Not Found"),"OK","Check Price") -> Check Price
A60: ="ORD"&TEXT(ROW()-1,"0000") -> ORD0059 | B60: 45420 | C60: Talha Ahmed | D60: Quetta | E60: East | F60: Printer Paper | G60: Electronics | H60: 1 | I60: 1200 | J60: 0.15 | K60: =H60*I60*(1-J60) -> 1020 | L60: Zain | M60: Debit Card | N60: =IF(I60=_xlfn.XLOOKUP(F60,Lists!$D$2:$D$13,Lists!$E$2:$E$13,"Not Found"),"OK","Check Price") -> OK
A61: ="ORD"&TEXT(ROW()-1,"0000") -> ORD0060 | B61: 45762 | C61: Maham Khan | D61: Hyderabad | E61: South | F61: Calculator | G61: =_xlfn.XLOOKUP(F61,Lists!$J$2:$J$13,Lists!$K$2:$K$13,"Not Found") -> Office Supplies | H61: 7 | I61: =_xlfn.XLOOKUP(F61,Lists!$D$2:$D$13,Lists!$E$2:$E$13,"Not Found") -> 1500 | J61: 0.15 | K61: =H61*I61*(1-J61) -> 8925 | L61: Bilal | M61: Bank Transfer | N61: =IF(I61=_xlfn.XLOOKUP(F61,Lists!$D$2:$D$13,Lists!$E$2:$E$13,"Not Found"),"OK","Check Price") -> OK
A62: ="ORD"&TEXT(ROW()-1,"0000") -> ORD0061 | B62: 45890 | C62: Talha Ahmed | D62: Karachi | E62: South West | F62: Mouse | G62: Furniture | H62: 7 | I62: 350 | J62: 0.1 | K62: =H62*I62*(1-J62) -> 2205 | L62: Bilal | M62: Cash | N62: =IF(I62=_xlfn.XLOOKUP(F62,Lists!$D$2:$D$13,Lists!$E$2:$E$13,"Not Found"),"OK","Check Price") -> Check Price
A63: ="ORD"&TEXT(ROW()-1,"0000") -> ORD0062 | B63: 45755 | C63: Ahmed Raza | D63: Islamabad | E63: South West | F63: USB Drive | G63: Electronics | H63: 1 | I63: 4000 | J63: 0.15 | K63: =H63*I63*(1-J63) -> 3400 | L63: Bilal | M63: Credit Card | N63: =IF(I63=_xlfn.XLOOKUP(F63,Lists!$D$2:$D$13,Lists!$E$2:$E$13,"Not Found"),"OK","Check Price") -> Check Price
A64: ="ORD"&TEXT(ROW()-1,"0000") -> ORD0063 | B64: 45656 | C64: Hamza Ali | D64: Faisalabad | E64: South West | F64: Printer | G64: Office Supplies | H64: 6 | I64: 30000 | J64: 0.15 | K64: =H64*I64*(1-J64) -> 153000 | L64: Hina | M64: Bank Transfer | N64: =IF(I64=_xlfn.XLOOKUP(F64,Lists!$D$2:$D$13,Lists!$E$2:$E$13,"Not Found"),"OK","Check Price") -> Check Price
A65: ="ORD"&TEXT(ROW()-1,"0000") -> ORD0064 | B65: 45920 | C65: Fatima Noor | D65: Lahore | E65: South East | F65: Office Desk | G65: =_xlfn.XLOOKUP(F65,Lists!$J$2:$J$13,Lists!$K$2:$K$13,"Not Found") -> Furniture | H65: 3 | I65: =_xlfn.XLOOKUP(F65,Lists!$D$2:$D$13,Lists!$E$2:$E$13,"Not Found") -> 22000 | J65: 0.15 | K65: =H65*I65*(1-J65) -> 56100 | L65: Ali | M65: Cash | N65: =IF(I65=_xlfn.XLOOKUP(F65,Lists!$D$2:$D$13,Lists!$E$2:$E$13,"Not Found"),"OK","Check Price") -> OK
A66: ="ORD"&TEXT(ROW()-1,"0000") -> ORD0065 | B66: 45474 | C66: Fatima Noor | D66: Islamabad | E66: South West | F66: Office Chair | G66: Electronics | H66: 4 | I66: 30000 | J66: 0.1 | K66: =H66*I66*(1-J66) -> 108000 | L66: Fatima | M66: Bank Transfer | N66: =IF(I66=_xlfn.XLOOKUP(F66,Lists!$D$2:$D$13,Lists!$E$2:$E$13,"Not Found"),"OK","Check Price") -> Check Price
A67: ="ORD"&TEXT(ROW()-1,"0000") -> ORD0066 | B67: 45556 | C67: Ali Khan | D67: Lahore | E67: West | F67: Printer | G67: Office Supplies | H67: 3 | I67: 1500 | J67: 0.15 | K67: =H67*I67*(1-J67) -> 3825 | L67: Usman | M67: Credit Card | N67: =IF(I67=_xlfn.XLOOKUP(F67,Lists!$D$2:$D$13,Lists!$E$2:$E$13,"Not Found"),"OK","Check Price") -> Check Price
A68: ="ORD"&TEXT(ROW()-1,"0000") -> ORD0067 | B68: 45642 | C68: Ali Khan | D68: Hyderabad | E68: South West | F68: Mouse | G68: Office Supplies | H68: 9 | I68: 12000 | J68: 0.2 | K68: =H68*I68*(1-J68) -> 86400 | L68: Sara | M68: Debit Card | N68: =IF(I68=_xlfn.XLOOKUP(F68,Lists!$D$2:$D$13,Lists!$E$2:$E$13,"Not Found"),"OK","Check Price") -> Check Price
A69: ="ORD"&TEXT(ROW()-1,"0000") -> ORD0068 | B69: 45978 | C69: Mariam Noor | D69: Sialkot | E69: South East | F69: USB Drive | G69: Electronics | H69: 6 | I69: 85000 | J69: 0.2 | K69: =H69*I69*(1-J69) -> 408000 | L69: Usman | M69: Credit Card | N69: =IF(I69=_xlfn.XLOOKUP(F69,Lists!$D$2:$D$13,Lists!$E$2:$E$13,"Not Found"),"OK","Check Price") -> Check Price
A70: ="ORD"&TEXT(ROW()-1,"0000") -> ORD0069 | B70: 45500 | C70: Hina Shah | D70: Quetta | E70: South West | F70: Printer | G70: Furniture | H70: 1 | I70: 30000 | J70: 0.15 | K70: =H70*I70*(1-J70) -> 25500 | L70: Zain | M70: Bank Transfer | N70: =IF(I70=_xlfn.XLOOKUP(F70,Lists!$D$2:$D$13,Lists!$E$2:$E$13,"Not Found"),"OK","Check Price") -> Check Price
A71: ="ORD"&TEXT(ROW()-1,"0000") -> ORD0070 | B71: 45633 | C71: Ayesha Malik | D71: Lahore | E71: West | F71: Monitor | G71: Electronics | H71: 1 | I71: 30000 | J71: 0.25 | K71: =H71*I71*(1-J71) -> 22500 | L71: Sara | M71: Credit Card | N71: =IF(I71=_xlfn.XLOOKUP(F71,Lists!$D$2:$D$13,Lists!$E$2:$E$13,"Not Found"),"OK","Check Price") -> OK
A72: ="ORD"&TEXT(ROW()-1,"0000") -> ORD0071 | B72: 45969 | C72: Sara Ahmed | D72: Peshawar | E72: North | F72: Printer Paper | G72: Office Supplies | H72: 1 | I72: 4000 | J72: 0.1 | K72: =H72*I72*(1-J72) -> 3600 | L72: Ali | M72: Debit Card | N72: =IF(I72=_xlfn.XLOOKUP(F72,Lists!$D$2:$D$13,Lists!$E$2:$E$13,"Not Found"),"OK","Check Price") -> Check Price
A73: ="ORD"&TEXT(ROW()-1,"0000") -> ORD0072 | B73: 45736 | C73: Sana Ali | D73: Lahore | E73: West | F73: Printer Paper | G73: Furniture | H73: 9 | I73: 5000 | J73: 0.25 | K73: =H73*I73*(1-J73) -> 33750 | L73: Zain | M73: Credit Card | N73: =IF(I73=_xlfn.XLOOKUP(F73,Lists!$D$2:$D$13,Lists!$E$2:$E$13,"Not Found"),"OK","Check Price") -> Check Price
A74: ="ORD"&TEXT(ROW()-1,"0000") -> ORD0073 | B74: 45729 | C74: Sara Ahmed | D74: Hyderabad | E74: West | F74: Monitor | G74: Electronics | H74: 10 | I74: 350 | J74: 0.25 | K74: =H74*I74*(1-J74) -> 2625 | L74: Ali | M74: Credit Card | N74: =IF(I74=_xlfn.XLOOKUP(F74,Lists!$D$2:$D$13,Lists!$E$2:$E$13,"Not Found"),"OK","Check Price") -> Check Price
A75: ="ORD"&TEXT(ROW()-1,"0000") -> ORD0074 | B75: 45911 | C75: Mariam Noor | D75: Quetta | E75: East | F75: Calculator | G75: =_xlfn.XLOOKUP(F75,Lists!$J$2:$J$13,Lists!$K$2:$K$13,"Not Found") -> Office Supplies | H75: 3 | I75: =_xlfn.XLOOKUP(F75,Lists!$D$2:$D$13,Lists!$E$2:$E$13,"Not Found") -> 1500 | J75: 0.05 | K75: =H75*I75*(1-J75) -> 4275 | L75: Ahmed | M75: Debit Card | N75: =IF(I75=_xlfn.XLOOKUP(F75,Lists!$D$2:$D$13,Lists!$E$2:$E$13,"Not Found"),"OK","Check Price") -> OK
A76: ="ORD"&TEXT(ROW()-1,"0000") -> ORD0075 | B76: 45591 | C76: Ayesha Malik | D76: Quetta | E76: South East | F76: Notebook | G76: Furniture | H76: 3 | I76: 2000 | J76: 0.1 | K76: =H76*I76*(1-J76) -> 5400 | L76: Ahmed | M76: Cash | N76: =IF(I76=_xlfn.XLOOKUP(F76,Lists!$D$2:$D$13,Lists!$E$2:$E$13,"Not Found"),"OK","Check Price") -> Check Price
A77: ="ORD"&TEXT(ROW()-1,"0000") -> ORD0076 | B77: 45408 | C77: Mariam Noor | D77: Hyderabad | E77: North | F77: USB Drive | G77: Office Supplies | H77: 9 | I77: 22000 | J77: 0.2 | K77: =H77*I77*(1-J77) -> 158400 | L77: Zain | M77: Bank Transfer | N77: =IF(I77=_xlfn.XLOOKUP(F77,Lists!$D$2:$D$13,Lists!$E$2:$E$13,"Not Found"),"OK","Check Price") -> Check Price
A78: ="ORD"&TEXT(ROW()-1,"0000") -> ORD0077 | B78: 45324 | C78: Usman Khan | D78: Sialkot | E78: West | F78: Headphones | G78: Furniture | H78: 7 | I78: 5000 | J78: 0.2 | K78: =H78*I78*(1-J78) -> 28000 | L78: Bilal | M78: Credit Card | N78: =IF(I78=_xlfn.XLOOKUP(F78,Lists!$D$2:$D$13,Lists!$E$2:$E$13,"Not Found"),"OK","Check Price") -> OK
A79: ="ORD"&TEXT(ROW()-1,"0000") -> ORD0078 | B79: 45469 | C79: Bilal Ahmed | D79: Karachi | E79: East | F79: Monitor | G79: Office Supplies | H79: 9 | I79: 30000 | J79: 0.15 | K79: =H79*I79*(1-J79) -> 229500 | L79: Ali | M79: Bank Transfer | N79: =IF(I79=_xlfn.XLOOKUP(F79,Lists!$D$2:$D$13,Lists!$E$2:$E$13,"Not Found"),"OK","Check Price") -> OK
A80: ="ORD"&TEXT(ROW()-1,"0000") -> ORD0079 | B80: 45702 | C80: Sara Ahmed | D80: Karachi | E80: South East | F80: Mouse | G80: Electronics | H80: 8 | I80: 2500 | J80: 0.15 | K80: =H80*I80*(1-J80) -> 17000 | L80: Zain | M80: Debit Card | N80: =IF(I80=_xlfn.XLOOKUP(F80,Lists!$D$2:$D$13,Lists!$E$2:$E$13,"Not Found"),"OK","Check Price") -> OK
A81: ="ORD"&TEXT(ROW()-1,"0000") -> ORD0080 | B81: 45842 | C81: Owais Raza | D81: Islamabad | E81: South | F81: Laptop | G81: =_xlfn.XLOOKUP(F81,Lists!$J$2:$J$13,Lists!$K$2:$K$13,"Not Found") -> Electronics | H81: 10 | I81: =_xlfn.XLOOKUP(F81,Lists!$D$2:$D$13,Lists!$E$2:$E$13,"Not Found") -> 85000 | J81: 0.2 | K81: =H81*I81*(1-J81) -> 680000 | L81: Hina | M81: Debit Card | N81: =IF(I81=_xlfn.XLOOKUP(F81,Lists!$D$2:$D$13,Lists!$E$2:$E$13,"Not Found"),"OK","Check Price") -> OK
A82: ="ORD"&TEXT(ROW()-1,"0000") -> ORD0081 | B82: 45612 | C82: Hina Shah | D82: Hyderabad | E82: South | F82: Printer Paper | G82: Furniture | H82: 3 | I82: 22000 | J82: 0.05 | K82: =H82*I82*(1-J82) -> 62700 | L82: Ali | M82: Debit Card | N82: =IF(I82=_xlfn.XLOOKUP(F82,Lists!$D$2:$D$13,Lists!$E$2:$E$13,"Not Found"),"OK","Check Price") -> Check Price
A83: ="ORD"&TEXT(ROW()-1,"0000") -> ORD0082 | B83: 45608 | C83: Ali Khan | D83: Rawalpindi | E83: South East | F83: Office Desk | G83: =_xlfn.XLOOKUP(F83,Lists!$J$2:$J$13,Lists!$K$2:$K$13,"Not Found") -> Furniture | H83: 4 | I83: =_xlfn.XLOOKUP(F83,Lists!$D$2:$D$13,Lists!$E$2:$E$13,"Not Found") -> 22000 | J83: 0.1 | K83: =H83*I83*(1-J83) -> 79200 | L83: Hina | M83: Debit Card | N83: =IF(I83=_xlfn.XLOOKUP(F83,Lists!$D$2:$D$13,Lists!$E$2:$E$13,"Not Found"),"OK","Check Price") -> OK
A84: ="ORD"&TEXT(ROW()-1,"0000") -> ORD0083 | B84: 45342 | C84: Zain Malik | D84: Hyderabad | E84: South | F84: Printer Paper | G84: Office Supplies | H84: 4 | I84: 28000 | J84: 0.15 | K84: =H84*I84*(1-J84) -> 95200 | L84: Zain | M84: Credit Card | N84: =IF(I84=_xlfn.XLOOKUP(F84,Lists!$D$2:$D$13,Lists!$E$2:$E$13,"Not Found"),"OK","Check Price") -> Check Price
A85: ="ORD"&TEXT(ROW()-1,"0000") -> ORD0084 | B85: 45357 | C85: Ahmed Raza | D85: Hyderabad | E85: South West | F85: Notebook | G85: Furniture | H85: 8 | I85: 350 | J85: 0.1 | K85: =H85*I85*(1-J85) -> 2520 | L85: Fatima | M85: Credit Card | N85: =IF(I85=_xlfn.XLOOKUP(F85,Lists!$D$2:$D$13,Lists!$E$2:$E$13,"Not Found"),"OK","Check Price") -> OK
A86: ="ORD"&TEXT(ROW()-1,"0000") -> ORD0085 | B86: 45453 | C86: Hina Shah | D86: Sialkot | E86: West | F86: Notebook | G86: Electronics | H86: 4 | I86: 30000 | J86: 0.1 | K86: =H86*I86*(1-J86) -> 108000 | L86: Ahmed | M86: Debit Card | N86: =IF(I86=_xlfn.XLOOKUP(F86,Lists!$D$2:$D$13,Lists!$E$2:$E$13,"Not Found"),"OK","Check Price") -> Check Price
A87: ="ORD"&TEXT(ROW()-1,"0000") -> ORD0086 | B87: 45556 | C87: Saad Raza | D87: Quetta | E87: North | F87: Printer | G87: Furniture | H87: 6 | I87: 2500 | J87: 0.05 | K87: =H87*I87*(1-J87) -> 14250 | L87: Hina | M87: Debit Card | N87: =IF(I87=_xlfn.XLOOKUP(F87,Lists!$D$2:$D$13,Lists!$E$2:$E$13,"Not Found"),"OK","Check Price") -> Check Price
A88: ="ORD"&TEXT(ROW()-1,"0000") -> ORD0087 | B88: 45419 | C88: Owais Raza | D88: Multan | E88: South West | F88: Monitor | G88: Electronics | H88: 4 | I88: 85000 | J88: 0.05 | K88: =H88*I88*(1-J88) -> 323000 | L88: Hina | M88: Debit Card | N88: =IF(I88=_xlfn.XLOOKUP(F88,Lists!$D$2:$D$13,Lists!$E$2:$E$13,"Not Found"),"OK","Check Price") -> Check Price
A89: ="ORD"&TEXT(ROW()-1,"0000") -> ORD0088 | B89: 45338 | C89: Hassan Ahmed | D89: Multan | E89: East | F89: Mouse | G89: Office Supplies | H89: 9 | I89: 85000 | J89: 0.05 | K89: =H89*I89*(1-J89) -> 726750 | L89: Ayesha | M89: Cash | N89: =IF(I89=_xlfn.XLOOKUP(F89,Lists!$D$2:$D$13,Lists!$E$2:$E$13,"Not Found"),"OK","Check Price") -> Check Price
A90: ="ORD"&TEXT(ROW()-1,"0000") -> ORD0089 | B90: 45916 | C90: Zain Malik | D90: Lahore | E90: West | F90: Calculator | G90: =_xlfn.XLOOKUP(F90,Lists!$J$2:$J$13,Lists!$K$2:$K$13,"Not Found") -> Office Supplies | H90: 2 | I90: =_xlfn.XLOOKUP(F90,Lists!$D$2:$D$13,Lists!$E$2:$E$13,"Not Found") -> 1500 | J90: 0.05 | K90: =H90*I90*(1-J90) -> 2850 | L90: Usman | M90: Debit Card | N90: =IF(I90=_xlfn.XLOOKUP(F90,Lists!$D$2:$D$13,Lists!$E$2:$E$13,"Not Found"),"OK","Check Price") -> OK
A91: ="ORD"&TEXT(ROW()-1,"0000") -> ORD0090 | B91: 45860 | C91: Ali Khan | D91: Sialkot | E91: South | F91: Keyboard | G91: Furniture | H91: 2 | I91: 2000 | J91: 0.25 | K91: =H91*I91*(1-J91) -> 3000 | L91: Ali | M91: Credit Card | N91: =IF(I91=_xlfn.XLOOKUP(F91,Lists!$D$2:$D$13,Lists!$E$2:$E$13,"Not Found"),"OK","Check Price") -> Check Price
A92: ="ORD"&TEXT(ROW()-1,"0000") -> ORD0091 | B92: 45666 | C92: Ayesha Malik | D92: Multan | E92: South West | F92: Office Desk | G92: =_xlfn.XLOOKUP(F92,Lists!$J$2:$J$13,Lists!$K$2:$K$13,"Not Found") -> Furniture | H92: 3 | I92: =_xlfn.XLOOKUP(F92,Lists!$D$2:$D$13,Lists!$E$2:$E$13,"Not Found") -> 22000 | J92: 0.15 | K92: =H92*I92*(1-J92) -> 56100 | L92: Sara | M92: Cash | N92: =IF(I92=_xlfn.XLOOKUP(F92,Lists!$D$2:$D$13,Lists!$E$2:$E$13,"Not Found"),"OK","Check Price") -> OK
A93: ="ORD"&TEXT(ROW()-1,"0000") -> ORD0092 | B93: 45312 | C93: Hina Shah | D93: Sialkot | E93: North | F93: Mouse | G93: Electronics | H93: 2 | I93: 2500 | J93: 0.2 | K93: =H93*I93*(1-J93) -> 4000 | L93: Hina | M93: Debit Card | N93: =IF(I93=_xlfn.XLOOKUP(F93,Lists!$D$2:$D$13,Lists!$E$2:$E$13,"Not Found"),"OK","Check Price") -> OK
A94: ="ORD"&TEXT(ROW()-1,"0000") -> ORD0093 | B94: 45522 | C94: Owais Raza | D94: Faisalabad | E94: West | F94: Mouse | G94: Electronics | H94: 5 | I94: 4000 | J94: 0.2 | K94: =H94*I94*(1-J94) -> 16000 | L94: Ali | M94: Cash | N94: =IF(I94=_xlfn.XLOOKUP(F94,Lists!$D$2:$D$13,Lists!$E$2:$E$13,"Not Found"),"OK","Check Price") -> Check Price
A95: ="ORD"&TEXT(ROW()-1,"0000") -> ORD0094 | B95: 45561 | C95: Laiba Khan | D95: Sialkot | E95: West | F95: Keyboard | G95: Electronics | H95: 7 | I95: 2500 | J95: 0.1 | K95: =H95*I95*(1-J95) -> 15750 | L95: Ahmed | M95: Cash | N95: =IF(I95=_xlfn.XLOOKUP(F95,Lists!$D$2:$D$13,Lists!$E$2:$E$13,"Not Found"),"OK","Check Price") -> Check Price
A96: ="ORD"&TEXT(ROW()-1,"0000") -> ORD0095 | B96: 45936 | C96: Laiba Khan | D96: Islamabad | E96: West | F96: Keyboard | G96: Furniture | H96: 3 | I96: 85000 | J96: 0.2 | K96: =H96*I96*(1-J96) -> 204000 | L96: Hamza | M96: Bank Transfer | N96: =IF(I96=_xlfn.XLOOKUP(F96,Lists!$D$2:$D$13,Lists!$E$2:$E$13,"Not Found"),"OK","Check Price") -> Check Price
A97: ="ORD"&TEXT(ROW()-1,"0000") -> ORD0096 | B97: 45976 | C97: Saad Raza | D97: Faisalabad | E97: South East | F97: USB Drive | G97: Office Supplies | H97: 6 | I97: 1500 | J97: 0.05 | K97: =H97*I97*(1-J97) -> 8550 | L97: Hina | M97: Credit Card | N97: =IF(I97=_xlfn.XLOOKUP(F97,Lists!$D$2:$D$13,Lists!$E$2:$E$13,"Not Found"),"OK","Check Price") -> Check Price
A98: ="ORD"&TEXT(ROW()-1,"0000") -> ORD0097 | B98: 45339 | C98: Talha Ahmed | D98: Peshawar | E98: South East | F98: Keyboard | G98: Furniture | H98: 7 | I98: 30000 | J98: 0.1 | K98: =H98*I98*(1-J98) -> 189000 | L98: Fatima | M98: Credit Card | N98: =IF(I98=_xlfn.XLOOKUP(F98,Lists!$D$2:$D$13,Lists!$E$2:$E$13,"Not Found"),"OK","Check Price") -> Check Price
A99: ="ORD"&TEXT(ROW()-1,"0000") -> ORD0098 | B99: 45683 | C99: Hamza Ali | D99: Sialkot | E99: South East | F99: Notebook | G99: Office Supplies | H99: 9 | I99: 1200 | J99: 0.25 | K99: =H99*I99*(1-J99) -> 8100 | L99: Sara | M99: Debit Card | N99: =IF(I99=_xlfn.XLOOKUP(F99,Lists!$D$2:$D$13,Lists!$E$2:$E$13,"Not Found"),"OK","Check Price") -> Check Price
A100: ="ORD"&TEXT(ROW()-1,"0000") -> ORD0099 | B100: 45748 | C100: Fatima Noor | D100: Karachi | E100: North | F100: Mouse | G100: Furniture | H100: 8 | I100: 4000 | J100: 0.15 | K100: =H100*I100*(1-J100) -> 27200 | L100: Zain | M100: Debit Card | N100: =IF(I100=_xlfn.XLOOKUP(F100,Lists!$D$2:$D$13,Lists!$E$2:$E$13,"Not Found"),"OK","Check Price") -> Check Price
...

Sheet Analysis
A1: Total Sales | B1: Total Orders | C1: Total Quantity | D1: Average Order Value
A2: =SUM(SalesData[Total Sales]) -> 1.0146586e+08 | B2: =COUNTA(SalesData[Order ID]) -> 1000 | C2: =SUM(SalesData[Quantity]) -> 5479 | D2: =A2/B2 -> 101465.86

Sheet Pivots
A1: Sales by Months | E1: Sales by Products | H1: Sales by SalesPerson Performance | K1: Sales by Region
A2: Years (Order Date) | B2: Months (Order Date) | C2: Sum of Total Sales | E2: Products | F2: Sum of Total Sales | H2: Sales Person | I2: Sum of Total Sales | K2: Region | L2: Sum of Total Sales
A3: 2024 | B3: Jan | C3: 2845590 | E3: Calculator | F3: 525000 | H3: Ahmed | I3: 8392347.5 | K3: East | L3: 20611850
B4: Feb | C4: 4937840 | E4: Headphones | F4: 7897787.5 | H4: Ali | I4: 16249705 | K4: North | L4: 15508848
B5: Mar | C5: 4619320 | E5: Keyboard | F5: 6567997.5 | H5: Ayesha | I5: 10631538 | K5: South | L5: 14372818
B6: Apr | C6: 5452800 | E6: Laptop | F6: 36222750 | H6: Bilal | I6: 8695777.5 | K6: South East | L6: 16387498
B7: May | C7: 3810852.5 | E7: Monitor | F7: 6006547.5 | H7: Fatima | I7: 10275082 | K7: West | L7: 16156142
B8: Jun | C8: 3921877.5 | E8: Mouse | F8: 6076387.5 | H8: Hamza | I8: 12407278 | K8: South West | L8: 18428702
B9: Jul | C9: 4318820 | E9: Notebook | F9: 5507170 | H9: Hina | I9: 9324817.5 | K9: Grand Total | L9: 1.0146586e+08
B10: Aug | C10: 9422005 | E10: Office Chair | F10: 6941902.5 | H10: Sara | I10: 6091995
B11: Sep | C11: 4090307.5 | E11: Office Desk | F11: 9735000 | H11: Usman | I11: 8404842.5 | K11: Sales by Category
B12: Oct | C12: 3211980 | E12: Printer | F12: 4929470 | H12: Zain | I12: 10992475 | K12: Category | L12: Sum of Total Sales
B13: Nov | C13: 3227587.5 | E13: Printer Paper | F13: 5659342.5 | H13: Grand Total | I13: 1.0146586e+08 | K13: Electronics | L13: 54927260
B14: Dec | C14: 5216190 | E14: USB Drive | F14: 5396502.5 | K14: Furniture | L14: 28693095
A15: 2024 Total | C15: 55075170 | E15: Grand Total | F15: 1.0146586e+08 | K15: Office Supplies | L15: 17845502
A16: 2025 | B16: Jan | C16: 4249992.5 | K16: Grand Total | L16: 1.0146586e+08
B17: Feb | C17: 3768090
B18: Mar | C18: 3061625
B19: Apr | C19: 4163080
B20: May | C20: 3576615
B21: Jun | C21: 2449110
B22: Jul | C22: 5823465
B23: Aug | C23: 2987350
B24: Sep | C24: 3604637.5
B25: Oct | C25: 4408370
B26: Nov | C26: 4759722.5
B27: Dec | C27: 3538630
A28: 2025 Total | C28: 46390688
A29: Grand Total | C29: 1.0146586e+08
A31: Total Sales | B31: Total ID's | C31: Order's Sold
A32: Sum of Total Sales | B32: Count of Order ID | C32: Sum of Quantity
A33: 1.0146586e+08 | B33: 1000 | C33: 5479

Sheet Dashboard
B2: SALES PERFORMANCE DASHBOARD
B4: Total Sales | D4: Total Quantity Sold
B5: =GETPIVOTDATA("Sum of Total Sales",Pivots!$A$32) -> 1.0146586e+08 | D5: =GETPIVOTDATA("Sum of Quantity",Pivots!$A$32) -> 5479
B7: Total Orders | D7: Average Order Value
B8: =GETPIVOTDATA("Count of Order ID",Pivots!$A$32) -> 1000 | D8: =GETPIVOTDATA("Sum of Total Sales",Pivots!$A$32)/GETPIVOTDATA("Count of Order ID",Pivots!$A$32) -> 101465.86

Sheet Insights & Recommendations
B2: Key Business Insights
B3: Overall Performance: The dashboard recorded total sales of 101.47 million across 1,000 orders, with 5,479 units sold and an average order value of 101,465.86.
B4: Yearly Comparison: Sales decreased from 55.08 million in 2024 to 46.39 million in 2025, a decline of approximately 15.77%.
B5: Category Performance: Electronics was the highest-selling category at 54.93 million, while Office Supplies recorded the lowest sales at 17.85 million.
B6: Product Performance: Laptop generated the highest product sales at 36.22 million, while Calculator recorded the lowest at 0.53 million.
B7: Regional Performance: East was the top-performing region with sales of 20.61 million, while South recorded the lowest regional sales at 14.37 million.
B8: Salesperson Performance: Ali generated the highest sales at 16.25 million, while Sara recorded the lowest at 6.09 million.
B9: Monthly Trends: August was the highest-sales month in 2024, while January was the lowest. In 2025, July was the highest-sales month and June was the lowest.
B10: Interactive Dashboard: Slicers for Category, Month, Product, Region, and Salesperson allow users to explore sales performance dynamically. KPI cards update with the selected filters.
B12: Business Recommendations
B13: Investigate the Year-over-Year Sales Decline: Compare monthly, product, and regional sales across 2024 and 2025 to identify where performance declined and which areas need further investigation.
B15: Analyze Regional Performance: Study the sales patterns and product mix in East, the highest-performing region, and investigate demand, product availability, and sales coverage in South, the lowest-performing region.
... B24: Use Interactive Reporting for Decisions: Regularly use the dashboard's KPI cards and slicers to monitor sales, orders, quantity sold, and average order value across products, regions, months, categories, and salespersons.
